<data id="hospitalar_v2" instanceID="uuid:2d7dd3a3-89a1-4131-86f6-9892889e85ce" version="1" submissionDate="2025-07-30T12:49:29.655+02:00" isComplete="true" markedAsCompleteDate="2025-07-30T12:49:29.655+02:00" xmlns="http://opendatakit.org/submissions"><start>2025-07-30T12:19:44.058+02:00</start><end>2025-07-30T12:49:24.833+02:00</end><deviceid>collect:Nxah3jujWvS8G22p</deviceid><Unidade_sanitaria>CS_Zimpeto</Unidade_sanitaria><Codigo_do_tecnico>IDSO1GB</Codigo_do_tecnico><Dados_demograficos><DATE1>2025-07-30T12:19:44.058+02:00</DATE1><DATE2>2025-07-30</DATE2><data_inclusao /><Local_de_inclusao>Triagem</Local_de_inclusao><codigo_paciente>IDS0100635</codigo_paciente><sexo>Feminino</sexo><conhece_nascimento_data>sim</conhece_nascimento_data><data_nascimento>2015-06-08</data_nascimento><idade /><tipo_idade /><idade2>10</idade2><Escolaridade>Primario_ou_Alfabetizacao</Escolaridade><Escolaridade_other /><Marital>SOLTEIRO</Marital><Profissao /><Profissao_other /><Relegiao>Protestante_Envagelica</Relegiao><Relegiao_other /><provincia_de_residencia>Maputo_Provincia</provincia_de_residencia><distrito_residencia>MATOLA</distrito_residencia><Pais /><bairro>Muhalazi</bairro><Gravidez>Nao</Gravidez><ssim_meses /><Peso>28.9</Peso><Altura>1.55</Altura><testado_malaria>nao</testado_malaria><resultado_malaria /><Algu_vez_teste_de_HIV>sim</Algu_vez_teste_de_HIV><data_de_testagem>2025-07-30</data_de_testagem><hiv>Negativo</hiv><Esta_em_TARV /><FMSP>nao</FMSP></Dados_demograficos><nota111><temperat>36.7</temperat><FRE_RESPIRATORIA>20</FRE_RESPIRATORIA><Frequencia_cardiaca>90</Frequencia_cardiaca><Tensao_arterial /><Sintomas>Diarreia</Sintomas><nr_dias_febre /><nest_mom_febre /><outro_sintoma /><tipo_hemoragia /><data_inic_sint>2025-07-28</data_inic_sint><tempo_duracao>1</tempo_duracao></nota111><Influenza><nota122 /><BCG /><data23 /><Polio>sim</Polio><Data24>2015-06-09</Data24></Influenza><nota123><Dose_1 /><Data25 /><Dose_2 /><Data26 /><Dose_277 /><Data268 /><Sarampo /><Data27 /><Gripe /><Data28 /><SARS_CoV_2 /><Dose_SARS /><Data29 /><Marca_da_vacina /><Febre_Amarela /></nota123><nota124><Hospitalizado /><Data30 /><Motivo_Hospitalizado /><Motivo_Hospitalizado_other /></nota124><nota126><doenca_cronica /><Doen_repirat /><Doen_repirat_other /><Doe_Hepatica_cronica /><Doe_Renal_Cronica /><Doe_Neuromuscular /><Diabetes /><Doe_Cardiovascular /><Foi_diagnost_TB_ulti_ano /><Data40 /><Tratamen_ultimas_48h /><Tratamen_ult_48h_other /><colheu_amos /></nota126><Salmonella><Pac_resp_si_mesmo /><Q_rel_paciente /><Q_rel_paciente_other /></Salmonella><note5><Tom_med_US /><Ssim_ind_med /><antibioticos_toma_tomou /><antibioticos_toma_tomou_other /><antibioticos_toma_t_data /><Opac_rec_al_medic /><Ssim_ind_medic /><Ssim_ind_medic_other /><antibioticos_toma_tomou1 /></note5><note6><Foi_encam_US /><DIAG_FEITO /><DIAG_FEITO_other /><ATFAD_pacient /><APOS_CONS_HOJE /><HA_INFOR_REPOT /><colheu_amostra_febre /></note6><Colera><episodios_diarreia>3_Ou_mais_episodios</episodios_diarreia><outro_patogeno>N sabe</outro_patogeno><fezes_Aquosas>sim</fezes_Aquosas><fezes_Peixe>sim</fezes_Peixe><fezes_Arroz>sim</fezes_Arroz><fezes_Sangue>nao</fezes_Sangue><fezes_Muco>sim</fezes_Muco><vomitos>nao</vomitos><episodios_vomitos /><dor_abdominal>nao</dor_abdominal><caimbras /><desidratacao>sim</desidratacao><classificacao_desidratacao>Moderada</classificacao_desidratacao><teve_contacto>nao</teve_contacto><aglomerado>Outro</aglomerado><aglomerado_other>N&#227;o esteve em aglomerado</aglomerado_other><fonte_agua>Fontenaria</fonte_agua><fonte_agua_other /><purifica_agua>nao</purifica_agua><purificador_agua_usado /><purificador_agua_usado_other /><local_necessidades_maiores>Outro</local_necessidades_maiores><local_necessidades_maiores_other>Pia</local_necessidades_maiores_other><vacinacao>nao</vacinacao><doses_vacina /><colheu_amostr_colera>sim</colheu_amostr_colera></Colera><n0:meta xmlns:n0="http://openrosa.org/xforms"><n0:instanceID>uuid:2d7dd3a3-89a1-4131-86f6-9892889e85ce</n0:instanceID></n0:meta></data>