<data id="frm_recep_amo" instanceID="uuid:0e4525dd-8e85-4e49-a22b-398a25b69dbd" version="1" submissionDate="2025-04-03T09:40:09.406+02:00" isComplete="true" markedAsCompleteDate="2025-04-03T09:40:09.406+02:00" xmlns="http://opendatakit.org/submissions"><Ident><DATE1>2025-04-03T09:00:36.007+02:00</DATE1><DATE2>2025-04-03</DATE2><Local>INS</Local><codigo_paciente>IDS0100320</codigo_paciente></Ident><n0:meta xmlns:n0="http://openrosa.org/xforms"><n0:instanceID>uuid:0e4525dd-8e85-4e49-a22b-398a25b69dbd</n0:instanceID></n0:meta></data>